{
    "status": 0,
    "message": [
    {
    "user_name": "匿名用户",
    "add_time": "2019-02-15T03:53:59.000Z",
    "content": "11111"
    },
    {
    "user_name": "匿名用户",
    "add_time": "2019-02-14T03:39:04.000Z",
    "content": "啊"
    },
    {
    "user_name": "匿名用户",
    "add_time": "2019-02-12T11:35:53.000Z",
    "content": "oklknkn"
    },
    {
    "user_name": "匿名用户",
    "add_time": "2019-02-11T07:01:25.000Z",
    "content": "ssssfd"
    },
    {
    "user_name": "匿名用户",
    "add_time": "2019-02-09T07:00:50.000Z",
    "content": "嘎嘎嘎嘎嘎过"
    },
    {
    "user_name": "匿名用户",
    "add_time": "2019-02-09T07:00:00.000Z",
    "content": "斤斤计较"
    },
    {
    "user_name": "匿名用户",
    "add_time": "2019-02-09T06:59:47.000Z",
    "content": "就很久很久"
    },
    {
    "user_name": "匿名用户",
    "add_time": "2019-02-09T06:58:42.000Z",
    "content": "快快快 解决"
    },
    {
    "user_name": "匿名用户",
    "add_time": "2019-02-09T06:58:14.000Z",
    "content": "干活干活干活干活干活干活干活 国家规划"
    },
    {
    "user_name": "匿名用户",
    "add_time": "2019-02-09T06:57:52.000Z",
    "content": "干活干活干活干活 快快快"
    }
    ]
    }